Changelog.rst
DEVELOPERS
LICENSE
MANIFEST.in
README
README.rst
distribute_setup.py
setup.py
version.txt
examples/compare_events.py
examples/dataset_xsec.py
examples/list_runs.py
examples/test1.py
examples/test2.py
examples/test3.py
examples/test4.py
examples/tutorialExample1.py
examples/tutorialExample2.py
examples/tutorialExample3.py
pyAMI/__init__.py
pyAMI/ami.py
pyAMI/auth.py
pyAMI/client.py
pyAMI/config.py
pyAMI/defaults.py
pyAMI/endpoint.py
pyAMI/exceptions.py
pyAMI/httpconnection.py
pyAMI/info.py
pyAMI/objects.py
pyAMI/query.py
pyAMI/schema.py
pyAMI/userdata.py
pyAMI/utils.py
pyAMI/webservices.py
pyAMI/xslt.py
pyAMI.egg-info/PKG-INFO
pyAMI.egg-info/SOURCES.txt
pyAMI.egg-info/dependency_links.txt
pyAMI.egg-info/entry_points.txt
pyAMI.egg-info/requires.txt
pyAMI.egg-info/top_level.txt
pyAMI/backports/__init__.py
pyAMI/backports/urllib2.py
pyAMI/extern/__init__.py
pyAMI/extern/argparse.py
pyAMI/extern/ZSI/ServiceContainer.py
pyAMI/extern/ZSI/ServiceProxy.py
pyAMI/extern/ZSI/TC.py
pyAMI/extern/ZSI/TCapache.py
pyAMI/extern/ZSI/TCcompound.py
pyAMI/extern/ZSI/TCnumbers.py
pyAMI/extern/ZSI/TCtimes.py
pyAMI/extern/ZSI/__init__.py
pyAMI/extern/ZSI/address.py
pyAMI/extern/ZSI/auth.py
pyAMI/extern/ZSI/client.py
pyAMI/extern/ZSI/digest_auth.py
pyAMI/extern/ZSI/dispatch.py
pyAMI/extern/ZSI/fault.py
pyAMI/extern/ZSI/parse.py
pyAMI/extern/ZSI/resolvers.py
pyAMI/extern/ZSI/schema.py
pyAMI/extern/ZSI/typeinterpreter.py
pyAMI/extern/ZSI/writer.py
pyAMI/extern/ZSI/generate/__init__.py
pyAMI/extern/ZSI/generate/commands.py
pyAMI/extern/ZSI/generate/containers.py
pyAMI/extern/ZSI/generate/pyclass.py
pyAMI/extern/ZSI/generate/utility.py
pyAMI/extern/ZSI/generate/wsdl2dispatch.py
pyAMI/extern/ZSI/generate/wsdl2python.py
pyAMI/extern/ZSI/twisted/WSresource.py
pyAMI/extern/ZSI/twisted/WSsecurity.py
pyAMI/extern/ZSI/twisted/__init__.py
pyAMI/extern/ZSI/twisted/client.py
pyAMI/extern/ZSI/wstools/Namespaces.py
pyAMI/extern/ZSI/wstools/TimeoutSocket.py
pyAMI/extern/ZSI/wstools/UserTuple.py
pyAMI/extern/ZSI/wstools/Utility.py
pyAMI/extern/ZSI/wstools/WSDLTools.py
pyAMI/extern/ZSI/wstools/XMLSchema.py
pyAMI/extern/ZSI/wstools/XMLname.py
