Metadata-Version: 1.0
Name: pyAMI
Version: 4.1.3
Summary: The ATLAS Metadata Interface
Home-page: https://atlas-ami.cern.ch/AMI/pyAMI/
Author: The AMI Team
Author-email: atlas-bookkeeping@cern.ch
License: GPLv3
Download-URL: http://pypi.python.org/packages/source/p/pyAMI/pyAMI-4.1.3.tar.gz
Platform: UNKNOWN
Classifier: Programming Language :: Python
Classifier: Topic :: Utilities
Classifier: Operating System :: POSIX :: Linux
Classifier: Development Status :: 5 - Production/Stable
Classifier: Intended Audience :: Science/Research
Classifier: Intended Audience :: Developers
Classifier: License :: OSI Approved :: GNU General Public License (GPL)
